hnxwidget/__init__.py
hnxwidget/_version.py
hnxwidget/example.py
hnxwidget/hypernetx_widget.py
hnxwidget/react_jupyter_widget.py
hnxwidget/stats.py
hnxwidget/util.py
hnxwidget/static/extension.js
hnxwidget/static/index.js
hnxwidget/static/index.js.map
hnxwidget-0.1.1b1.data/data/etc/jupyter/nbconfig/notebook.d/hnx-widget.json
hnxwidget-0.1.1b1.data/data/share/jupyter/nbextensions/hnx-widget/extension.js
hnxwidget-0.1.1b1.data/data/share/jupyter/nbextensions/hnx-widget/index.js
hnxwidget-0.1.1b1.data/data/share/jupyter/nbextensions/hnx-widget/index.js.map
hnxwidget-0.1.1b1.dist-info/METADATA
hnxwidget-0.1.1b1.dist-info/WHEEL
hnxwidget-0.1.1b1.dist-info/top_level.txt
hnxwidget-0.1.1b1.dist-info/RECORD
